dobato/__init__.py
dobato/__main__.py
dobato/dobato.py
dobato-1.0.0.dist-info/WHEEL
dobato-1.0.0.dist-info/METADATA
dobato-1.0.0.dist-info/RECORD
