Metadata-Version: 2.1
Name: dobato
Version: 1.0.0
Summary: Simple tool for discord BOT
Author: himkt
Author-email: himkt@klis.tsukuba.ac.jp
Requires-Python: >=3.6,<4.0
Classifier: Programming Language :: Python :: 3
Classifier: Programming Language :: Python :: 3.6
Classifier: Programming Language :: Python :: 3.7
Classifier: Programming Language :: Python :: 3.8
Classifier: Programming Language :: Python :: 3.9
